helloheart_airflow_utils/__init__.py
helloheart_airflow_utils/logging/README.md
helloheart_airflow_utils/logging/__init__.py
helloheart_airflow_utils/logging/log_config.py
helloheart_airflow_utils-0.2.5.dist-info/LICENSE
helloheart_airflow_utils-0.2.5.dist-info/METADATA
helloheart_airflow_utils-0.2.5.dist-info/WHEEL
helloheart_airflow_utils-0.2.5.dist-info/RECORD
