Metadata-Version: 2.1
Name: helloheart-airflow-utils
Version: 0.2.5
Summary: Apache Airflow Utilities
Home-page: https://github.com/Hello-Heart/helloheart-airflow-utils
License: MIT
Author: Ory Jonay
Author-email: ory.jonay@helloheart.com
Requires-Python: >=3.8,<3.12
Classifier: License :: OSI Approved :: MIT License
Classifier: Programming Language :: Python :: 3
Classifier: Programming Language :: Python :: 3.8
Classifier: Programming Language :: Python :: 3.9
Classifier: Programming Language :: Python :: 3.10
Classifier: Programming Language :: Python :: 3.11
Requires-Dist: apache-airflow (>=2,<3)
